jpscore.py
jpscore-0.0.9.dist-info/METADATA
jpscore-0.0.9.dist-info/WHEEL
jpscore-0.0.9.dist-info/entry_points.txt
jpscore-0.0.9.dist-info/top_level.txt
jpscore-0.0.9.dist-info/RECORD
