Metadata-Version: 2.1
Name: jpscore
Version: 0.0.9
Summary: A package for scoring prefecture COVID-19 policies in Japan
Home-page: https://github.com/y-takefuji/covid_score_japan
Author: yoshiyasu takefuji
Author-email: takefuji@keio.jp
License: UNKNOWN
Project-URL: Bug Tracker, https://github.com/y-takefuji/covid_score_japan
Platform: UNKNOWN
Classifier: Programming Language :: Python :: 3
Classifier: License :: OSI Approved :: MIT License
Classifier: Operating System :: OS Independent
Requires-Python: >=3.8
